lavish_hello/__init__.py
lavish_hello/main.py
lavish_and_shubham-0.2.dist-info/METADATA
lavish_and_shubham-0.2.dist-info/WHEEL
lavish_and_shubham-0.2.dist-info/top_level.txt
lavish_and_shubham-0.2.dist-info/RECORD
