Metadata-Version: 2.1
Name: lavish_and_shubham
Version: 0.2
Summary: Lavish and Shubham boss ka package ha.
